torch_stft/__init__.py
torch_stft/stft.py
torch_stft/util.py
torch_stft-0.1.4.dist-info/LICENSE
torch_stft-0.1.4.dist-info/METADATA
torch_stft-0.1.4.dist-info/WHEEL
torch_stft-0.1.4.dist-info/top_level.txt
torch_stft-0.1.4.dist-info/RECORD
