Metadata-Version: 2.1
Name: torch-stft
Version: 0.1.4
Summary: An STFT/iSTFT for PyTorch
Home-page: https://github.com/pseeth/torch-stft
Author: Prem Seetharaman
Author-email: prem@u.northwestern.edu
License: UNKNOWN
Platform: UNKNOWN
Classifier: Environment :: Plugins
Classifier: Intended Audience :: Developers
Classifier: Intended Audience :: Science/Research
Classifier: License :: OSI Approved :: BSD License
Classifier: Operating System :: MacOS :: MacOS X
Classifier: Operating System :: Microsoft :: Windows
Classifier: Operating System :: POSIX
Classifier: Programming Language :: C++
Classifier: Programming Language :: Python :: 3
Classifier: Topic :: Multimedia :: Sound/Audio
Classifier: Topic :: Scientific/Engineering :: Artificial Intelligence
Requires-Dist: numpy
Requires-Dist: scipy
Requires-Dist: librosa
